LICENSE
MANIFEST.in
README.md
setup.cfg
setup.py
versioneer.py
polarball/__init__.py
polarball/_version.py
polarball/polarball.py
polarball.egg-info/PKG-INFO
polarball.egg-info/SOURCES.txt
polarball.egg-info/dependency_links.txt
polarball.egg-info/requires.txt
polarball.egg-info/top_level.txt
polarball/data/__init__.py
polarball/io/__init__.py
polarball/utils/__init__.py
polarball/utils/file_utils.py
polarball/utils/logging.py
polarball/utils/package_data.py