Metadata-Version: 2.1
Name: polarball
Version: 0.0.2
Summary: The POLAR response sky interpolation tool
Home-page: https://github.com/POLAR-2/polarball
Author: J. Michael Burgess
Author-email: jburgess@mpe.mpg.de
License: GPL-2+
Project-URL: Bug Tracker, https://github.com/grburgess/polarball/issues
Project-URL: Source Code, https://github.com/grburgess/polarball
Platform: UNKNOWN
Classifier: Development Status :: 2 - Pre-Alpha
Classifier: Environment :: Console
Classifier: Intended Audience :: Science/Research
Classifier: License :: OSI Approved :: GNU General Public License v2 or later (GPLv2+)
Classifier: Operating System :: POSIX
Classifier: Programming Language :: Python :: 3.5
Classifier: Programming Language :: Python :: 3.6
Classifier: Programming Language :: Python :: 3.7
Classifier: Programming Language :: Python :: 3.8
Classifier: Topic :: Scientific/Engineering :: Physics
License-File: LICENSE
